arc_crawler/__init__.py
arc_crawler/reader/__init__.py
arc_crawler/reader/index.py
arc_crawler/reader/types.py
arc_crawler/scraping/__init__.py
arc_crawler/scraping/crawler.py
arc_crawler/scraping/decorators.py
arc_crawler/scraping/fetcher.py
arc_crawler/scraping/types.py
arc_crawler/utils/__init__.py
arc_crawler/utils/common.py
arc_crawler/utils/file.py
arc_crawler/utils/logger.py
arc_crawler/utils/timer.py
arc_crawler-0.1.1.dist-info/LICENSE
arc_crawler-0.1.1.dist-info/METADATA
arc_crawler-0.1.1.dist-info/WHEEL
arc_crawler-0.1.1.dist-info/RECORD
