Metadata-Version: 2.3
Name: arc-crawler
Version: 0.1.1
Summary: Configurable crawler for web-scraping
Keywords: scrape,crawl,test
Author: Amachoma
Author-email: as.derbin99@gmail.com
Requires-Python: >=3.9
Classifier: Development Status :: 2 - Pre-Alpha
Classifier: Programming Language :: Python
Classifier: Intended Audience :: Developers
Classifier: License :: OSI Approved :: MIT License
Classifier: Natural Language :: English
Requires-Dist: aiohttp (>=3.11.10,<4.0.0)
Requires-Dist: bs4 (>=0.0.2,<0.0.3)
